ip_whitelist/__init__.py
ip_whitelist/admin.py
ip_whitelist/apps.py
ip_whitelist/middleware.py
ip_whitelist/models.py
ip_whitelist/utils.py
ip_whitelist/validators.py
ip_whitelist/migrations/0001_initial.py
ip_whitelist/migrations/0002_auto_20220103_1123.py
ip_whitelist/migrations/0003_auto_20240212_1640.py
ip_whitelist/migrations/__init__.py
ip_whitelist/templates/ip_whitelist/admin/change_list.html
django_ip_whitelist-0.1.10.dist-info/LICENSE
django_ip_whitelist-0.1.10.dist-info/METADATA
django_ip_whitelist-0.1.10.dist-info/WHEEL
django_ip_whitelist-0.1.10.dist-info/top_level.txt
django_ip_whitelist-0.1.10.dist-info/RECORD
