Metadata-Version: 2.1
Name: django-ip-whitelist
Version: 0.1.10
Summary: A Django app to only allow access to certain pages based on IP addresses.
Home-page: https://github.com/maykinmedia/django-ip-whitelist
Author: Maykin Media
Author-email: support@maykinmedia.nl
License: MIT
Project-URL: Bug Tracker, https://github.com/maykinmedia/django-ip-whitelist/issues
Project-URL: Source Code, https://github.com/maykinmedia/django-ip-whitelist
Keywords: ip,whitelist,django
Classifier: Development Status :: 3 - Alpha
Classifier: Framework :: Django
Classifier: Framework :: Django :: 3.2
Classifier: Framework :: Django :: 4.1
Classifier: Framework :: Django :: 4.2
Classifier: Intended Audience :: Developers
Classifier: Operating System :: Unix
Classifier: Operating System :: MacOS
Classifier: Operating System :: Microsoft :: Windows
Classifier: Programming Language :: Python :: 3.8
Classifier: Programming Language :: Python :: 3.9
Classifier: Programming Language :: Python :: 3.10
Classifier: Programming Language :: Python :: 3.11
Classifier: Topic :: Software Development :: Libraries :: Python Modules
License-File: LICENSE
Requires-Dist: Django>=3.2
Requires-Dist: django-import-export
Requires-Dist: ipaddress
Requires-Dist: requests
